[
  {
    "a": "Unknown",
    "q": "Nangayo ko sa Ginooug buwak.\nGihatagan ko niyaug usa ka bandihadong bulak.\nNangayo ko sa Ginoo ug minute.\nGihatagan ko niyag usa ka-adlaw. Nangayu ko sa Ginoo ug anghel, \nIKAW iyang gihatag."
  },
  {
    "a": "Unknown",
    "q": "Ma U-Turn man akong mata sa uban.\nPero One-way ra ni kung mo pitik akong dughan."
  },
  {
    "a": "Unknown",
    "q": "Ang gugma mura na sya ogmath pagmakakita og greater than sa imoha ma i-less than jud ka."
  }
]
